BASE_dzne/__init__.py
BASE_dzne/__main__.py
BASE_dzne/core/__init__.py
BASE_dzne/core/legacy/__init__.py
BASE_dzne/core/legacy/aBASE/__init__.py
BASE_dzne/core/legacy/cBASE/__init__.py
BASE_dzne/core/legacy/libBASE/__init__.py
BASE_dzne/core/legacy/libBASE/config.py
BASE_dzne/core/legacy/libBASE/config.toml
BASE_dzne/core/legacy/libBASE/primer.toml
BASE_dzne/core/legacy/libBASE/core/IgBlastParser.py
BASE_dzne/core/legacy/libBASE/core/__init__.py
BASE_dzne/core/legacy/libBASE/core/varia.py
BASE_dzne/core/legacy/libBASE/primerdata/README
BASE_dzne/core/legacy/libBASE/primerdata/createPrimerDB.py
BASE_dzne/core/legacy/libBASE/primerdata/primer_created_manually.py
BASE_dzne/core/legacy/libBASE/primerdata/specPCR_primer_2019_04_14.xlsx
BASE_dzne/core/legacy/tests/SeqData.zip
BASE_dzne/core/legacy/tests/__init__.py
BASE_dzne/core/legacy/tests/aBASE-113-goal.xlsm
BASE_dzne/core/legacy/tests/aBASE-113-input.xlsx
BASE_dzne/core/legacy/tests/cBASE-113-goal.xlsx
BASE_dzne/core/legacy/tests/cBASE-113-input.xlsx
BASE_dzne/core/legacy/tests/test_legacy.py
BASE_dzne/tests/__init__.py
BASE_dzne/tests/test_1984.py
BASE_dzne-2.0.dist-info/LICENSE.txt
BASE_dzne-2.0.dist-info/METADATA
BASE_dzne-2.0.dist-info/WHEEL
BASE_dzne-2.0.dist-info/top_level.txt
BASE_dzne-2.0.dist-info/RECORD
