Metadata-Version: 2.2
Name: BASE_dzne
Version: 2.0
Summary: Brain Antibody Sequence Evaluation (BASE)
Author-email: Johannes Horler <johannes.horler@charite.de>
License:                     GNU GENERAL PUBLIC LICENSE
Project-URL: Documentation, https://pypi.org/project/BASE_dzne/
Project-URL: Download, https://pypi.org/project/BASE_dzne/#files
Project-URL: Index, https://pypi.org/project/BASE_dzne/
Project-URL: Paper, https://pubmed.ncbi.nlm.nih.gov/33032524/
Project-URL: Source, https://github.com/johanneshorler/BASE_dzne/
Classifier: Development Status :: 5 - Production/Stable
Classifier: License :: OSI Approved :: MIT License
Classifier: Natural Language :: English
Classifier: Natural Language :: German
Classifier: Operating System :: OS Independent
Classifier: Programming Language :: Python
Classifier: Programming Language :: Python :: 3
Classifier: Programming Language :: Python :: 3 :: Only
Requires-Python: >=3.10
License-File: LICENSE.txt
Requires-Dist: biopython==1.77
Requires-Dist: click>=8.1.7
Requires-Dist: compareworkbooks>=0.2
Requires-Dist: openpyxl>=3.0.3
Requires-Dist: tomli>=2.0.1
